<?xml version="1.0" encoding="UTF-8"?>
<!DOCTYPE CourseDB SYSTEM "ROCS.dtd">
<CourseDB timestamp="1238421894" semesternumber="200909" semesterdesc="Fall 09">
  <Course name="PROJECTS IN ARCH &amp; ENV DE" dept="ARCH" num="2940" credmin="1" credmax="6" gradetype="SU">
    <Section crn="44307" num="0" students="0" seats="0" closed="true"/>
  </Course>
  <Course name="COMPUTER SCIENCE I" dept="CSCI" num="1100" credmin="4" credmax="4" gradetype="NORM">
    <Section crn="42571" num="1" students="6" seats="30" closed="false">
      <Period type="LEC" instructor="Hardwick" start="900" end="950">
	<Day>0</Day>
	<Day>3</Day>
      </Period>
      <Period type="LAB" instructor="Staff" start="1000" end="1150">
	<Day>0</Day>
	<Day>3</Day>
      </Period>
    </Section>
  </Course>
  <CrossListing seats="0">
    <CRN>45307</CRN>
    <CRN>45308</CRN>
  </CrossListing>
  <Course name="COGNITIVE ROBOTICS II" dept="PHIL" num="4961" credmin="4" credmax="4" gradetype="NORM">
    <Section crn="45307" num="1" students="1" seats="0" closed="true">
      <Period type="LEC" instructor="Van Heuvel" start="1400" end="1550">
	<Day>1</Day>
	<Day>4</Day>
      </Period>
    </Section>
    <Note>PERMISSION OF INSTRUCTOR</Note>
    <Note>MEETS WITH PSYC 4961</Note>
  </Course>
  <Course name="COGNITIVE ROBOTICS I I" dept="PSYC" num="4961" credmin="4" credmax="4" gradetype="NORM">
    <Section crn="45308" num="1" students="2" seats="0" closed="true">
      <Period type="LEC" instructor="Van Heuvel" start="1400" end="155">
	<Day>1</Day>
	<Day>4</Day>
      </Period>
    </Section>
    <Note>PERMISSION OF INSTRUCTOR</Note>
    <Note>MEETS WITH PHIL 4961</Note>
  </Course>
</CourseDB>
